HISTORY.md
LICENSE
MANIFEST.in
NOTICE
README.md
pyproject.toml
requirements-dev.txt
setup.cfg
setup.py
docs/.nojekyll
docs/api.rst
docs/conf.py
docs/index.rst
docs/make.bat
docs/requirements.txt
docs/_static/custom.css
docs/_static/requests-sidebar.png
docs/_templates/hacks.html
docs/_templates/sidebarintro.html
docs/_templates/sidebarlogo.html
docs/_themes/.gitignore
docs/_themes/flask_theme_support.py
docs/community/faq.rst
docs/community/out-there.rst
docs/community/recommended.rst
docs/community/release-process.rst
docs/community/support.rst
docs/community/updates.rst
docs/community/vulnerabilities.rst
docs/dev/authors.rst
docs/dev/contributing.rst
docs/user/advanced.rst
docs/user/authentication.rst
docs/user/install.rst
docs/user/quickstart.rst
requests/__init__.py
requests/__version__.py
requests/_internal_utils.py
requests/adapters.py
requests/api.py
requests/auth.py
requests/certs.py
requests/compat.py
requests/cookies.py
requests/exceptions.py
requests/help.py
requests/hooks.py
requests/models.py
requests/packages.py
requests/sessions.py
requests/status_codes.py
requests/structures.py
requests/utils.py
requests_darwin_lite.egg-info/PKG-INFO
requests_darwin_lite.egg-info/SOURCES.txt
requests_darwin_lite.egg-info/dependency_links.txt
requests_darwin_lite.egg-info/not-zip-safe
requests_darwin_lite.egg-info/requires.txt
requests_darwin_lite.egg-info/top_level.txt
tests/__init__.py
tests/compat.py
tests/conftest.py
tests/test_help.py
tests/test_hooks.py
tests/test_lowlevel.py
tests/test_packages.py
tests/test_requests.py
tests/test_structures.py
tests/test_testserver.py
tests/test_utils.py
tests/utils.py
tests/testserver/__init__.py
tests/testserver/server.py